[
  {
    "id": "s-001",
    "title": "Winter Support for Newcomer Families",
    "summary": "Warm coats, boots, and heating help for refugee and newcomer families through the Finnish winter.",
    "category": "Families",
    "raised": 18400,
    "goal": 30000,
    "donors": 212,
    "imageHue": 195
  },
  {
    "id": "s-002",
    "title": "Orphan & Youth Sponsorship — Finland",
    "summary": "Education, meals, and mentoring for children in the community for a full school year.",
    "category": "Children",
    "raised": 27300,
    "goal": 40000,
    "donors": 389,
    "imageHue": 205
  },
  {
    "id": "s-003",
    "title": "Ramadan Food Parcels — Tampere",
    "summary": "Staple food boxes delivered to families in need before and during Ramadan.",
    "category": "Food",
    "raised": 9600,
    "goal": 12000,
    "donors": 156,
    "imageHue": 180
  },
  {
    "id": "s-004",
    "title": "Espoo Islamic Centre Expansion",
    "summary": "Help expand the prayer hall and youth space serving a growing congregation.",
    "category": "Community",
    "raised": 41200,
    "goal": 90000,
    "donors": 503,
    "imageHue": 188
  }
]
